datarum/__init__.py
datarum/converter.py
datarum/wending.py
datarum-0.5.1.dist-info/DESCRIPTION.rst
datarum-0.5.1.dist-info/METADATA
datarum-0.5.1.dist-info/RECORD
datarum-0.5.1.dist-info/WHEEL
datarum-0.5.1.dist-info/metadata.json
datarum-0.5.1.dist-info/top_level.txt
