Metadata-Version: 2.0
Name: datarum
Version: 0.5.1
Summary: Datárum is a small python library to convert Gregorian dates to Wending, an Old English variant on the French Republican calendar, for use in various projects.
Home-page: https://github.com/Autophagy/datarum
Author: Mika Naylor (Autophagy)
Author-email: mail@autophagy.io
License: UNKNOWN
Platform: UNKNOWN
Classifier: Development Status :: 3 - Alpha
Classifier: License :: OSI Approved :: MIT License
Classifier: Programming Language :: Python :: 3
Classifier: Programming Language :: Python :: 3.6
Requires-Python: >=3
Requires-Dist: parse
